Isa_Mini/Isa_Mini.py
Isa_Mini/__init__.py
Isa_Mini/main.py
isamini-0.3.5.dist-info/licenses/COPYING
isamini-0.3.5.dist-info/licenses/COPYING.LESSER
isamini-0.3.5.dist-info/METADATA
isamini-0.3.5.dist-info/WHEEL
isamini-0.3.5.dist-info/top_level.txt
isamini-0.3.5.dist-info/RECORD
